Blue2Factor/Authentication.py
Blue2Factor/__init__.py
Blue2Factor/tests/__init__.py
Blue2Factor-0.1.5.dist-info/LICENSE
Blue2Factor-0.1.5.dist-info/METADATA
Blue2Factor-0.1.5.dist-info/WHEEL
Blue2Factor-0.1.5.dist-info/top_level.txt
Blue2Factor-0.1.5.dist-info/RECORD
