Metadata-Version: 2.1
Name: Blue2Factor
Version: 0.1.5
Summary: Used to implement Blue2Factor
Home-page: https://www.blue2factor.com
Author: Christopher McLain
Author-email: chris@blue2factor.com
Project-URL: Bug Tracker, https://github.com/bk89686/PyB2f/issues
Classifier: Programming Language :: Python :: 3
Classifier: License :: OSI Approved :: MIT License
Classifier: Operating System :: OS Independent
Requires-Python: >=3.6
License-File: LICENSE
